{"name":"persistmgr","parms":[{"name":"PersistAction","label":"Persist Action:","listitems":[{"code":"1","text":"Add persistent XML","ui":"Add current XML as a persistent profile","requires":{"osx":"","osxEnd":"","mx":"4.1","api":"","osxSpecific":"","osxSpecificList":"","osxExclude":"","osxExcludeEnd":""}},{"code":"2","text":"Remove persistent XML","ui":"Remove the specified persistent profile","requires":{"osx":"","osxEnd":"","mx":"4.1","api":"","osxSpecific":"","osxSpecificList":"","osxExclude":"","osxExcludeEnd":""}},{"code":"3","text":"Enable persistent XML","ui":"Enable the specified persistent profile","requires":{"osx":"","osxEnd":"","mx":"4.2","api":"","osxSpecific":"","osxSpecificList":"","osxExclude":"","osxExcludeEnd":""}},{"code":"4","text":"Disable persistent XML","ui":"Disable the specified persistent profile","requires":{"osx":"","osxEnd":"","mx":"4.2","api":"","osxSpecific":"","osxSpecificList":"","osxExclude":"","osxExcludeEnd":""}}]},{"name":"PersistAsName","label":"Persist As Name:","requires":{"osx":"","osxEnd":"","mx":"4.1","api":"","osxSpecific":"","osxSpecificList":"","osxExclude":"","osxExcludeEnd":""}},{"name":"PersistAsVersion","label":"Persist As Version:","requires":{"osx":"","osxEnd":"","mx":"4.2","api":"","osxSpecific":"","osxSpecificList":"","osxExclude":"","osxExcludeEnd":""}},{"name":"PersistAsOrder","label":"Persist As Order:","requires":{"osx":"","osxEnd":"","mx":"4.2","api":"","osxSpecific":"","osxSpecificList":"","osxExclude":"","osxExcludeEnd":""}},{"name":"PersistIfError","label":"Persist If Error?:","requires":{"mx":"4.2","api":"","osx":""},"selected":true}]}